fastapidevelop/__init__.py
fastapidevelop/__version__.py
fastapidevelop-0.0.1.dist-info/LICENSE
fastapidevelop-0.0.1.dist-info/METADATA
fastapidevelop-0.0.1.dist-info/WHEEL
fastapidevelop-0.0.1.dist-info/top_level.txt
fastapidevelop-0.0.1.dist-info/RECORD
